{
  "project_info": {
    "project_number": "242419485392",
    "firebase_url": "https://vacancy-page-v2-default-rtdb.firebaseio.com",
    "project_id": "vacancy-page-v2",
    "storage_bucket": "vacancy-page-v2.firebasestorage.app"
  },
  "client": [
    {
      "client_info": {
        "mobilesdk_app_id": "1:242419485392:android:ba45be3ff8dbd72e876cd5",
        "android_client_info": {
          "package_name": "com.bitx.tuchambaapp"
        }
      },
      "oauth_client": [],
      "api_key": [
        {
          "current_key": "AIzaSyBGwfNygrs3SdFWBpCjplN_ELupAYQywpw"
        }
      ],
      "services": {
        "appinvite_service": {
          "other_platform_oauth_client": []
        }
      }
    }
  ],
  "configuration_version": "1"
}